.coveragerc
.travis.yml
LICENSE
MANIFEST.in
README.rst
setup.cfg
setup.py
Mopidy_Yamaha.egg-info/PKG-INFO
Mopidy_Yamaha.egg-info/SOURCES.txt
Mopidy_Yamaha.egg-info/dependency_links.txt
Mopidy_Yamaha.egg-info/entry_points.txt
Mopidy_Yamaha.egg-info/not-zip-safe
Mopidy_Yamaha.egg-info/requires.txt
Mopidy_Yamaha.egg-info/top_level.txt
mopidy_yamaha/__init__.py
mopidy_yamaha/ext.conf
mopidy_yamaha/mixer.py
mopidy_yamaha/talker.py
tests/__init__.py
tests/example_responses.py
tests/test_extension.py
tests/test_mixer.py
tests/test_talker.py