Metadata-Version: 1.1
Name: Mopidy-Yamaha
Version: 0.1.0
Summary: Mopidy extension for controlling volume on Yamaha receivers
Home-page: https://github.com/knutz3n/mopidy-yamaha
Author: Johannes Knutsen
Author-email: johannes@knutsen.me
License: Apache License, Version 2.0
Platform: UNKNOWN
Classifier: Environment :: No Input/Output (Daemon)
Classifier: Intended Audience :: End Users/Desktop
Classifier: License :: OSI Approved :: Apache Software License
Classifier: Operating System :: OS Independent
Classifier: Programming Language :: Python :: 2
Classifier: Topic :: Multimedia :: Sound/Audio :: Players
